YongPythonZuoKexuejisuan/README.md
YongPythonZuoKexuejisuan/__init__.py
YongPythonZuoKexuejisuan/__main__.py
YongPythonZuoKexuejisuan/file.epub
YongPythonZuoKexuejisuan/index.html
YongPythonZuoKexuejisuan/css/__init__.py
YongPythonZuoKexuejisuan/css/annotations.css
YongPythonZuoKexuejisuan/css/main.css
YongPythonZuoKexuejisuan/css/normalize.css
YongPythonZuoKexuejisuan/css/popup.css
YongPythonZuoKexuejisuan/font/__init__.py
YongPythonZuoKexuejisuan/font/fontello.eot
YongPythonZuoKexuejisuan/font/fontello.svg
YongPythonZuoKexuejisuan/font/fontello.ttf
YongPythonZuoKexuejisuan/font/fontello.woff
YongPythonZuoKexuejisuan/img/__init__.py
YongPythonZuoKexuejisuan/img/annotator-glyph-sprite.png
YongPythonZuoKexuejisuan/img/annotator-icon-sprite.png
YongPythonZuoKexuejisuan/img/apple-touch-icon.png
YongPythonZuoKexuejisuan/img/cancelfullscreen.png
YongPythonZuoKexuejisuan/img/close.png
YongPythonZuoKexuejisuan/img/fullscreen.png
YongPythonZuoKexuejisuan/img/loader.gif
YongPythonZuoKexuejisuan/img/menu-icon.png
YongPythonZuoKexuejisuan/img/save.png
YongPythonZuoKexuejisuan/img/saved.png
YongPythonZuoKexuejisuan/img/settings-s.png
YongPythonZuoKexuejisuan/img/settings.png
YongPythonZuoKexuejisuan/img/star.png
YongPythonZuoKexuejisuan/js/__init__.py
YongPythonZuoKexuejisuan/js/epub.js
YongPythonZuoKexuejisuan/js/epub.min.js
YongPythonZuoKexuejisuan/js/epub.min.map
YongPythonZuoKexuejisuan/js/hooks.min.js
YongPythonZuoKexuejisuan/js/hooks.min.map
YongPythonZuoKexuejisuan/js/reader.js
YongPythonZuoKexuejisuan/js/reader.js.map
YongPythonZuoKexuejisuan/js/reader.min.js
YongPythonZuoKexuejisuan/js/reader.min.map
YongPythonZuoKexuejisuan/js/hooks/__init__.py
YongPythonZuoKexuejisuan/js/hooks/extensions/__init__.py
YongPythonZuoKexuejisuan/js/hooks/extensions/highlight.js
YongPythonZuoKexuejisuan/js/libs/__init__.py
YongPythonZuoKexuejisuan/js/libs/jquery.min.js
YongPythonZuoKexuejisuan/js/libs/localforage.min.js
YongPythonZuoKexuejisuan/js/libs/screenfull.js
yong_python_zuo_kexuejisuan-2024.2.29.0.dist-info/METADATA
yong_python_zuo_kexuejisuan-2024.2.29.0.dist-info/WHEEL
yong_python_zuo_kexuejisuan-2024.2.29.0.dist-info/entry_points.txt
yong_python_zuo_kexuejisuan-2024.2.29.0.dist-info/top_level.txt
yong_python_zuo_kexuejisuan-2024.2.29.0.dist-info/RECORD
